atlasreader/__init__.py
atlasreader/_version.py
atlasreader/atlasreader.py
atlasreader/cli.py
atlasreader/data/README.md
atlasreader/data/prepare_atlases.py
atlasreader/data/atlases/atlas_aal.nii.gz
atlasreader/data/atlases/atlas_aicha.nii.gz
atlasreader/data/atlases/atlas_desikan_killiany.nii.gz
atlasreader/data/atlases/atlas_destrieux.nii.gz
atlasreader/data/atlases/atlas_harvard_oxford.nii.gz
atlasreader/data/atlases/atlas_juelich.nii.gz
atlasreader/data/atlases/atlas_marsatlas.nii.gz
atlasreader/data/atlases/atlas_neuromorphometrics.nii.gz
atlasreader/data/atlases/atlas_talairach_ba.nii.gz
atlasreader/data/atlases/atlas_talairach_gyrus.nii.gz
atlasreader/data/atlases/labels_aal.csv
atlasreader/data/atlases/labels_aicha.csv
atlasreader/data/atlases/labels_desikan_killiany.csv
atlasreader/data/atlases/labels_destrieux.csv
atlasreader/data/atlases/labels_harvard_oxford.csv
atlasreader/data/atlases/labels_juelich.csv
atlasreader/data/atlases/labels_marsatlas.csv
atlasreader/data/atlases/labels_neuromorphometrics.csv
atlasreader/data/atlases/labels_talairach_ba.csv
atlasreader/data/atlases/labels_talairach_gyrus.csv
atlasreader/data/templates/MNI152_T1_1mm_brain.nii.gz
atlasreader/data/templates/mni_icbm152_t1_tal_nlin_asym_09c_brain.nii.gz
atlasreader/tests/__init__.py
atlasreader/tests/conftest.py
atlasreader/tests/test_atlasreader.py
atlasreader/tests/test_cli.py
atlasreader/tests/data/collection_658/collection_metadata.json
atlasreader/tests/data/collection_658/image_10426.nii.gz
atlasreader/tests/data/collection_658/image_10426_metadata.json
atlasreader-0.3.2.dist-info/METADATA
atlasreader-0.3.2.dist-info/WHEEL
atlasreader-0.3.2.dist-info/entry_points.txt
atlasreader-0.3.2.dist-info/licenses/LICENSE
atlasreader-0.3.2.dist-info/RECORD
