Metadata-Version: 2.1
Name: atlasreader
Version: 0.3.2
Summary: A toolbox for generating cluster reports from statistical maps
Project-URL: Downloads, https://github.com/miykael/atlasreader/releases
Project-URL: Homepage, http://github.com/miykael/atlasreader
Maintainer-email: Michael Notter <michaelnotter@hotmail.com>
License: BSD-3-Clause
License-File: LICENSE
Classifier: Intended Audience :: Developers
Classifier: Intended Audience :: Science/Research
Classifier: License :: OSI Approved
Classifier: Operating System :: MacOS
Classifier: Operating System :: Microsoft :: Windows
Classifier: Operating System :: POSIX
Classifier: Operating System :: Unix
Classifier: Programming Language :: Python
Classifier: Programming Language :: Python :: 3.8
Classifier: Programming Language :: Python :: 3.9
Classifier: Programming Language :: Python :: 3.10
Classifier: Programming Language :: Python :: 3.11
Classifier: Programming Language :: Python :: 3.12
Classifier: Topic :: Scientific/Engineering
Classifier: Topic :: Software Development
Requires-Python: >=3.8
Requires-Dist: matplotlib>=3.7
Requires-Dist: nibabel>=5.0
Requires-Dist: nilearn>=0.10
Requires-Dist: numpy>=1.22.0
Requires-Dist: pandas>=2.0
Requires-Dist: scikit-image>=0.21.0
Requires-Dist: scikit-learn>=1.0
Requires-Dist: scipy>=1.10
Provides-Extra: dev
Requires-Dist: atlasreader[style,test]; extra == 'dev'
Provides-Extra: style
Requires-Dist: black; extra == 'style'
Requires-Dist: codespell; extra == 'style'
Requires-Dist: flake8; extra == 'style'
Requires-Dist: isort; extra == 'style'
Requires-Dist: pre-commit; extra == 'style'
Requires-Dist: tomli; extra == 'style'
Provides-Extra: test
Requires-Dist: coverage; extra == 'test'
Requires-Dist: nbval; extra == 'test'
Requires-Dist: pytest-cov; extra == 'test'
Requires-Dist: pytest>=6.0.0; extra == 'test'
Provides-Extra: tests
Requires-Dist: atlasreader[test]; extra == 'tests'
